{
	"type": "object",
	"properties": {
		"type": {
			"const": "linkReference"
		},
		"identifier": {
			"type": "string"
		},
		"label": {
			"anyOf": [
				{
					"type": "string"
				},
				{
					"type": "null"
				}
			]
		},
		"referenceType": {
			"anyOf": [
				{
					"type": "string"
				},
				{
					"type": "null"
				}
			]
		},
		"children": {
			"items": {
				"$ref": "./inline-node.json"
			},
			"type": "array",
			"additionalItems": false,
			"unevaluatedItems": false
		}
	},
	"required": [
		"type",
		"identifier",
		"label",
		"referenceType",
		"children"
	],
	"additionalProperties": false,
	"unevaluatedProperties": false
}
